starship_mcp/__init__.py
starship_mcp/__main__.py
starship_mcp/auto_populate.py
starship_mcp/starship_mcp.py
starship_mcp-0.1.9.dist-info/METADATA
starship_mcp-0.1.9.dist-info/WHEEL
starship_mcp-0.1.9.dist-info/entry_points.txt
starship_mcp-0.1.9.dist-info/top_level.txt
starship_mcp-0.1.9.dist-info/RECORD
