Metadata-Version: 2.4
Name: starship-mcp
Version: 0.1.9
Summary: STARSHIP MCP - Experiential Captain Identity Bridge
Author: Isaac
Requires-Python: >=3.8
Requires-Dist: fastmcp
Requires-Dist: starlog-mcp
Dynamic: requires-python
